slash_util/__init__.py
slash_util/_patch.py
slash_util/bot.py
slash_util/cog.py
slash_util/context.py
slash_util/core.py
slash_util/enums.py
slash_util/modal.py
slash_util-1.3.3.1.dist-info/LICENSE
slash_util-1.3.3.1.dist-info/METADATA
slash_util-1.3.3.1.dist-info/WHEEL
slash_util-1.3.3.1.dist-info/top_level.txt
slash_util-1.3.3.1.dist-info/RECORD
