Metadata-Version: 2.1
Name: slash-util
Version: 1.3.3.1
Summary: A small script allowing the use of application commands with discord.py v2.0
Home-page: https://github.com/XuaTheGrate/slash_util
Author: XuaTheGrate
Author-email: 17090652+XuaTheGrate@users.noreply.github.com
License: UNKNOWN
Project-URL: Bug Tracker, https://github.com/XuaTheGrate/slash_util/issues
Platform: UNKNOWN
Classifier: Development Status :: 5 - Production/Stable
Classifier: License :: OSI Approved :: MIT License
Classifier: Programming Language :: Python :: 3.8
Classifier: Programming Language :: Python :: 3.9
Classifier: Programming Language :: Python :: 3.10
Classifier: Topic :: Utilities
Classifier: Typing :: Typed
Requires-Python: >=3.8
License-File: LICENSE
Requires-Dist: discord.py (>=2.0.0a)
